cfngiam/__init__.py
cfngiam/main.py
cfngiam/unsupported.py
cfngiam/version.py
cfngiam/unsupported/AWSCodeBuild.json
cfngiam/unsupported/AWSCodeCommit.json
cfngiam/unsupported/AWSCodeDeploy.json
cfngiam/unsupported/AWSCodePipeline.json
cfngiam-0.4.5.dist-info/LICENSE
cfngiam-0.4.5.dist-info/METADATA
cfngiam-0.4.5.dist-info/WHEEL
cfngiam-0.4.5.dist-info/entry_points.txt
cfngiam-0.4.5.dist-info/top_level.txt
cfngiam-0.4.5.dist-info/zip-safe
cfngiam-0.4.5.dist-info/RECORD
