Metadata-Version: 2.1
Name: cfngiam
Version: 0.4.5
Summary: Generates an IAM policy for the CloudFormation base describe-type's schema
Home-page: https://github.com/Takenori-Kusaka/cfn-giam
Author: Takenori Kusaka
Author-email: takenori.kusaka@gmail.com
License: MIT
Keywords: aws
Classifier: Programming Language :: Python :: 3.7
License-File: LICENSE
Requires-Dist: requests (>=2.27.1)
Requires-Dist: boto3 (>=1.18.54)
Requires-Dist: numpy (>=1.21.0)
